{
    "value": {
        "VSCODE_GIT_ASKPASS_MAIN": "/Applications/Visual Studio Code.app/Contents/Resources/app/extensions/git/dist/askpass-main.js",
        "CONDA_EXE": "/Users/mt/opt/anaconda3/bin/conda",
        "ORIGINAL_XDG_CURRENT_DESKTOP": "undefined",
        "__CF_USER_TEXT_ENCODING": "0x1F5:0x0:0x0",
        "SHLVL": "1",
        "MallocNanoZone": "0",
        "VSCODE_INJECTION": "1",
        "LANG": "en_US.UTF-8",
        "SSH_AUTH_SOCK": "/private/tmp/com.apple.launchd.Ehmc7qLH2n/Listeners",
        "SHELL": "/bin/zsh",
        "LOGNAME": "mt",
        "VSCODE_GIT_ASKPASS_NODE": "/Applications/Visual Studio Code.app/Contents/Frameworks/Code Helper.app/Contents/MacOS/Code Helper",
        "PATH": "/Library/Frameworks/Python.framework/Versions/3.9/bin:/usr/local/bin:/usr/bin:/bin:/usr/sbin:/sbin:/Library/TeX/texbin:/Users/mt/opt/anaconda3/bin:/Users/mt/opt/anaconda3/condabin:/Library/Frameworks/Python.framework/Versions/3.9/bin:/Users/mt/Library/Application Support/Coursier/bin:/Users/mt/.cabal/bin:/Users/mt/.ghcup/bin:/opt/homebrew/bin:/Users/mt/Library/Application Support/Coursier/bin:/opt/homebrew/bin",
        "_CE_M": "",
        "JAVA_MAIN_CLASS_73136": "mill.main.client.MillClientMain",
        "TERM": "xterm-256color",
        "VSCODE_GIT_ASKPASS_EXTRA_ARGS": "--ms-enable-electron-run-as-node",
        "CONDA_SHLVL": "1",
        "JAVA_MAIN_CLASS_73151": "mill.main.MillServerMain",
        "CONDA_PYTHON_EXE": "/Users/mt/opt/anaconda3/bin/python",
        "XPC_SERVICE_NAME": "0",
        "TERM_PROGRAM": "vscode",
        "CONDA_DEFAULT_ENV": "base",
        "HOME": "/Users/mt",
        "COLORTERM": "truecolor",
        "COMMAND_MODE": "unix2003",
        "ZDOTDIR": "/Users/mt",
        "USER": "mt",
        "USER_ZDOTDIR": "/Users/mt",
        "XPC_FLAGS": "0x0",
        "TMPDIR": "/var/folders/m1/zc1zr8c94014qwl_yvcz6n100000gn/T/",
        "TERM_PROGRAM_VERSION": "1.73.1",
        "PWD": "/Users/mt/Documents/GitHub Projects/cs-problem-generator/minimalApplication-0.8.3",
        "GIT_ASKPASS": "/Applications/Visual Studio Code.app/Contents/Resources/app/extensions/git/dist/askpass.sh",
        "CONDA_PREFIX": "/Users/mt/opt/anaconda3",
        "VSCODE_GIT_IPC_HANDLE": "/var/folders/m1/zc1zr8c94014qwl_yvcz6n100000gn/T/vscode-git-a3319c9976.sock",
        "CONDA_PROMPT_MODIFIER": "(base) ",
        "_CE_CONDA": "",
        "__CFBundleIdentifier": "com.microsoft.VSCode"
    },
    "valueHash": 2052675503,
    "inputsHash": 166351905
}